letshelp_certbot/__init__.py
letshelp_certbot/apache.py
letshelp_certbot/apache_test.py
letshelp_certbot/testdata/super_secret_file.txt
letshelp_certbot/testdata/uncommonly_named_k3y
letshelp_certbot/testdata/uncommonly_named_p4sswd
letshelp_certbot/testdata/mods-available/ssl.load
letshelp_certbot/testdata/mods-enabled/ssl.load
letshelp_certbot-0.6.0.dist-info/DESCRIPTION.rst
letshelp_certbot-0.6.0.dist-info/METADATA
letshelp_certbot-0.6.0.dist-info/RECORD
letshelp_certbot-0.6.0.dist-info/WHEEL
letshelp_certbot-0.6.0.dist-info/entry_points.txt
letshelp_certbot-0.6.0.dist-info/metadata.json
letshelp_certbot-0.6.0.dist-info/top_level.txt
