Metadata-Version: 2.0
Name: letshelp-certbot
Version: 0.6.0
Summary: Let's help Certbot client
Home-page: https://github.com/letsencrypt/letsencrypt
Author: Certbot Project
Author-email: client-dev@letsencrypt.org
License: Apache License 2.0
Platform: UNKNOWN
Classifier: Development Status :: 3 - Alpha
Classifier: Intended Audience :: System Administrators
Classifier: License :: OSI Approved :: Apache Software License
Classifier: Operating System :: POSIX :: Linux
Classifier: Programming Language :: Python
Classifier: Programming Language :: Python :: 2
Classifier: Programming Language :: Python :: 2.6
Classifier: Programming Language :: Python :: 2.7
Classifier: Topic :: Internet :: WWW/HTTP
Classifier: Topic :: Security
Classifier: Topic :: System :: Installation/Setup
Classifier: Topic :: System :: Networking
Classifier: Topic :: System :: Systems Administration
Classifier: Topic :: Utilities
Requires-Dist: mock
Requires-Dist: setuptools
Provides-Extra: docs
Requires-Dist: Sphinx (>=1.0); extra == 'docs'
Requires-Dist: sphinx-rtd-theme; extra == 'docs'
